.gitignore
.readthedocs.yml
LICENSE
README.rst
setup.py
data/regression_data.hdf5
docs/Makefile
docs/conf.py
docs/cross_validation.ipynb
docs/index.rst
docs/install.rst
docs/matplotlibrc
docs/plotting.rst
docs/release.rst
docs/requirements.txt
hilearn/__init__.py
hilearn/version.py
hilearn.egg-info/PKG-INFO
hilearn.egg-info/SOURCES.txt
hilearn.egg-info/dependency_links.txt
hilearn.egg-info/entry_points.txt
hilearn.egg-info/requires.txt
hilearn.egg-info/top_level.txt
hilearn/mcmc/mcmc_sampler.py
hilearn/models/__init__.py
hilearn/models/cross_validation.py
hilearn/models/mix_linear_regression.py
hilearn/plot/__init__.py
hilearn/plot/base_plot.py
hilearn/plot/box_plot.py
hilearn/plot/curve_plot.py
hilearn/plot/dot_plot.py
hilearn/plot/seaborn_plot.py
hilearn/stats/__init__.py
hilearn/stats/base_stats.py
hilearn/utils/__init__.py
hilearn/utils/base.py
test/flexmix_comparison.R
tutorial/regression-clustering.rst
tutorial/tutorial_cross-validation.rst
tutorial/tutorial_plots.rst
tutorial/images/clustering_output_6_0.png
tutorial/images/cv.output_4_0.png
tutorial/images/cv.output_6_0.png
tutorial/images/plot.output_1_0.png
tutorial/images/plot.output_3_0.png
tutorial/images/plot.output_5_0.png
tutorial/images/regression_output_4_0.png