Metadata-Version: 1.0
Name: hilearn
Version: 0.2.1
Summary: HiLearn: A small library of machine learning methods.
Home-page: https://github.com/huangyh09/hilearn
Author: Yuanhua Huang
Author-email: yuanhua@hku.hk
License: Apache-2.0
Keywords: machine learning,data visualisation
Platform: UNKNOWN
